qympy/__init__.py
qympy/example/__init__.py
qympy/machine_learning/__init__.py
qympy/machine_learning/classical.py
qympy/machine_learning/quantum.py
qympy/quantum_circuit/__init__.py
qympy/quantum_circuit/sp_circuit.py
qympy/quantum_circuit/sp_gate.py
qympy/tests/__init__.py
qympy-1.5.0.dist-info/LICENSE
qympy-1.5.0.dist-info/METADATA
qympy-1.5.0.dist-info/WHEEL
qympy-1.5.0.dist-info/top_level.txt
qympy-1.5.0.dist-info/RECORD
