Metadata-Version: 2.1
Name: qympy
Version: 1.5.0
Summary: Symbolic Calculation of Quantum Computation with Sympy
Author-email: Yi-An Chen <r08222011@gmail.com>
License: MIT License
Project-URL: Homepage, https://github.com/r08222011/Qympy
Keywords: Sympy,Qiskit,Quantum
Classifier: License :: OSI Approved :: MIT License
Classifier: Programming Language :: Python :: 3
License-File: LICENSE
Requires-Dist: sympy
Requires-Dist: qiskit
Requires-Dist: pylatexenc
